dataflows_ckan/__init__.py
dataflows_ckan/helpers.py
dataflows_ckan/processors/__init__.py
dataflows_ckan/processors/dump_to_ckan.py
dataflows_ckan-0.3.9.dist-info/LICENSE.md
dataflows_ckan-0.3.9.dist-info/METADATA
dataflows_ckan-0.3.9.dist-info/WHEEL
dataflows_ckan-0.3.9.dist-info/RECORD
