Metadata-Version: 2.1
Name: dataflows-ckan
Version: 0.3.9
Summary: CKAN integration for Dataflows.
License: MIT
Author: Paul Walsh
Author-email: paul@walsh.co.il
Requires-Python: >=3.8,<4.0
Classifier: License :: OSI Approved :: MIT License
Classifier: Programming Language :: Python :: 3
Classifier: Programming Language :: Python :: 3.8
Classifier: Programming Language :: Python :: 3.9
Classifier: Programming Language :: Python :: 3.10
Classifier: Programming Language :: Python :: 3.11
Classifier: Programming Language :: Python :: 3.12
Requires-Dist: ckan-datapackage-tools (>=0.1.0,<0.2.0)
Requires-Dist: dataflows (>=0.5.0,<0.6.0)
Requires-Dist: datapackage (>=1.15.2,<2.0.0)
Requires-Dist: tableschema-ckan-datastore (>=1.1.1,<2.0.0)
